faker_pyspark/__init__.py
faker_pyspark/pyspark.py
faker_pyspark-0.8.0.dist-info/LICENSE
faker_pyspark-0.8.0.dist-info/METADATA
faker_pyspark-0.8.0.dist-info/WHEEL
faker_pyspark-0.8.0.dist-info/RECORD
