Metadata-Version: 2.1
Name: faker-pyspark
Version: 0.8.0
Summary: faker-pyspark is a PySpark DataFrame and Schema provider for the Faker python package
Home-page: https://github.com/spsoni/faker-pyspark
License: MIT
Keywords: Faker, PySpark
Author: Sury Soni
Author-email: github@suryasoni.info
Requires-Python: >=3.8.1,<4.0.0
Classifier: License :: OSI Approved :: MIT License
Classifier: Programming Language :: Python :: 3
Classifier: Programming Language :: Python :: 3.9
Classifier: Programming Language :: Python :: 3.10
Classifier: Programming Language :: Python :: 3.11
Project-URL: Repository, https://github.com/spsoni/faker-pyspark
